lighter/__init__.py
lighter/api_client.py
lighter/api_response.py
lighter/configuration.py
lighter/errors.py
lighter/exceptions.py
lighter/nonce_manager.py
lighter/py.typed
lighter/rest.py
lighter/signer_client.py
lighter/ws_client.py
lighter/api/__init__.py
lighter/api/account_api.py
lighter/api/announcement_api.py
lighter/api/block_api.py
lighter/api/bridge_api.py
lighter/api/candlestick_api.py
lighter/api/funding_api.py
lighter/api/info_api.py
lighter/api/notification_api.py
lighter/api/order_api.py
lighter/api/referral_api.py
lighter/api/root_api.py
lighter/api/transaction_api.py
lighter/models/__init__.py
lighter/models/account.py
lighter/models/account_api_keys.py
lighter/models/account_asset.py
lighter/models/account_limits.py
lighter/models/account_margin_stats.py
lighter/models/account_market_stats.py
lighter/models/account_metadata.py
lighter/models/account_metadatas.py
lighter/models/account_pn_l.py
lighter/models/account_position.py
lighter/models/account_stats.py
lighter/models/account_trade_stats.py
lighter/models/announcement.py
lighter/models/announcements.py
lighter/models/api_key.py
lighter/models/asset.py
lighter/models/asset_details.py
lighter/models/block.py
lighter/models/blocks.py
lighter/models/bridge.py
lighter/models/bridge_supported_network.py
lighter/models/candlestick.py
lighter/models/candlesticks.py
lighter/models/contract_address.py
lighter/models/current_height.py
lighter/models/cursor.py
lighter/models/daily_return.py
lighter/models/deposit_history.py
lighter/models/deposit_history_item.py
lighter/models/detailed_account.py
lighter/models/detailed_accounts.py
lighter/models/detailed_candlestick.py
lighter/models/enriched_tx.py
lighter/models/exchange_stats.py
lighter/models/export_data.py
lighter/models/funding.py
lighter/models/funding_rate.py
lighter/models/funding_rates.py
lighter/models/fundings.py
lighter/models/l1_metadata.py
lighter/models/l1_provider_info.py
lighter/models/liq_trade.py
lighter/models/liquidation.py
qubx_lighter_api-0.1.5.dist-info/licenses/LICENSE
qubx_lighter_api-0.1.5.dist-info/METADATA
qubx_lighter_api-0.1.5.dist-info/WHEEL
qubx_lighter_api-0.1.5.dist-info/top_level.txt
qubx_lighter_api-0.1.5.dist-info/RECORD
